{
  "cv": 19,
  "name": "libevent",
  "fqn": "libevent-nim.openpeeps.github.com",
  "current": "73d1d5c03d4bb471b444707f796539705359d810",
  "author": "George Lemon",
  "description": "Bindings for Libevent",
  "license": "MIT",
  "nim": "2.0.0",
  "srcDir": "src",
  "releases": [
    {
      "v": "0.1.2@73d1d5c03d4bb471b444707f796539705359d810^",
      "r": []
    },
    {
      "v": "0.1.1@ed143c000c72b9fc0ba0d101b62712688cc70a1c",
      "r": []
    },
    {
      "v": "0.1.0@68fca69dcbac10b21865319216839076bf0cb198",
      "r": []
    }
  ],
  "releaseCacheVersion": 19,
  "tags": true,
  "generatedAt": "2026-06-04T01:01:00Z",
  "allDeps": {
    "packages": [],
    "urls": [],
    "unresolved": []
  }
}