{
  "cv": 19,
  "name": "boogie",
  "fqn": "boogie.openpeeps.github.com",
  "current": "03ca2f74ce81b6cb7769fb4bfcfb27ea10f2dab6",
  "author": "George Lemon",
  "description": "A suite of WAL-based data stores",
  "license": "LGPL-3.0-or-later",
  "nim": "2.0.0",
  "srcDir": "src",
  "releases": [
    {
      "v": "0.1.0@0a9356ebb458568751cba8cc20ca527fcaa7c98a",
      "r": [
        "sorta",
        "flatty",
        "threading",
        "openparser"
      ]
    }
  ],
  "releaseCacheVersion": 19,
  "tags": true,
  "generatedAt": "2026-07-14T00:34:25Z",
  "allDeps": {
    "packages": [
      "flatty",
      "nimsimd",
      "openparser",
      "sorta",
      "threading"
    ],
    "urls": [],
    "unresolved": []
  }
}